{
    "nodes": [
        {
            "id": "Define",
            "group": 1,
            "step": "Design Phase"
        },
        {
            "id": "Collect",
            "group": 2,
            "step": "AI Capability"
        },
        {
            "id": "Text File (From)",
            "group": 3,
            "step": "AI Input (From)"
        },
        {
            "id": "Text File (To)",
            "group": 4,
            "step": "AI Output (To)"
        }
    ],
    "links": [
        {
            "source": "Define",
            "target": "Collect"
        },
        {
            "source": "Collect",
            "target": "Text File (From)"
        },
        {
            "source": "Text File (From)",
            "target": "Text File (To)"
        }
    ]
}