{
    "nodes": [
        {
            "id": "Ideate",
            "group": 1,
            "step": "Design Phase"
        },
        {
            "id": "Prototype",
            "group": 1,
            "step": "Design Phase"
        },
        {
            "id": "Release",
            "group": 1,
            "step": "Design Phase"
        },
        {
            "id": "Generate",
            "group": 2,
            "step": "AI Capability"
        },
        {
            "id": "Image File (From)",
            "group": 3,
            "step": "AI Input (From)"
        },
        {
            "id": "Prompt (From)",
            "group": 3,
            "step": "AI Input (From)"
        },
        {
            "id": "Video File (To)",
            "group": 4,
            "step": "AI Output (To)"
        },
        {
            "id": "Image File (To)",
            "group": 4,
            "step": "AI Output (To)"
        },
        {
            "id": "Illustration (To)",
            "group": 4,
            "step": "AI Output (To)"
        }
    ],
    "links": [
        {
            "source": "Ideate",
            "target": "Generate"
        },
        {
            "source": "Generate",
            "target": "Image File (From)"
        },
        {
            "source": "Image File (From)",
            "target": "Video File (To)"
        },
        {
            "source": "Generate",
            "target": "Prompt (From)"
        },
        {
            "source": "Prompt (From)",
            "target": "Image File (To)"
        },
        {
            "source": "Prompt (From)",
            "target": "Illustration (To)"
        },
        {
            "source": "Prototype",
            "target": "Generate"
        },
        {
            "source": "Release",
            "target": "Generate"
        }
    ]
}